LICENSE.txt
MANIFEST.in
README.rst
setup.cfg
setup.py
geerefet/__init__.py
geerefet/calcs.py
geerefet/daily.py
geerefet/hourly.py
geerefet/units.py
geerefet/utils.py
geerefet.egg-info/PKG-INFO
geerefet.egg-info/SOURCES.txt
geerefet.egg-info/dependency_links.txt
geerefet.egg-info/requires.txt
geerefet.egg-info/top_level.txt
geerefet/__pycache__/__init__.cpython-36.pyc
geerefet/__pycache__/calcs.cpython-36.pyc
geerefet/__pycache__/daily.cpython-36.pyc
geerefet/__pycache__/hourly.cpython-36.pyc
geerefet/__pycache__/units.cpython-36.pyc
geerefet/__pycache__/utils.cpython-36.pyc